sparse_uls/__init__.py
sparse_uls/lp.py
sparse_uls/uls.py
sparse_uls/util.py
sparse_uls-6.3.dist-info/METADATA
sparse_uls-6.3.dist-info/WHEEL
sparse_uls-6.3.dist-info/top_level.txt
sparse_uls-6.3.dist-info/RECORD
