Metadata-Version: 2.1
Name: sparse-uls
Version: 6.3
Summary: optimize norm with underdetermined system equality constraint
Home-page: https://github.com/khanhhhh/sparse-uls
Author: Nguyen Ngoc Khanh
Author-email: nguyenngockhanh.pbc@gmail.com
License: UNKNOWN
Platform: UNKNOWN
